{
  "source":"src",
  "destination":"docs",

  "assets":[
    {"name":"css", "title":"CSS Dependencies"},
    {"name":"images", "title":"Image Dependencies"},
    {"name":"js", "title":"JavaScript Dependencies"}

  ],

  "chapters":[

    {"name":"index", "title":"Table of Contents"},

    {"name":"introduction", "title":"Introduction"},

    {"name":"hunter", "title":"The Hunter"},
    {"name":"adventurer", "title":"The Adventurer"},
    {"name":"soldier", "title":"The Soldier"},

    {"name":"knight", "title":"The Knight of Virtue"},
    {"name":"gentleman", "title":"Lady and Gentleman"},
    {"name":"officer", "title":"The Officer"},

    {"name":"intellectual", "title":"The Intellectual"},
    {"name":"humanitarian", "title":"The Humanitarian"},

    {"name":"ultra", "title":"The Ultra"},
    {"name":"superhero", "title":"The Superhero"},
    {"name":"philosopher", "title":"The Philosopher"},


    {"name":"skeptic", "title":"The Skeptic"},
    {"name":"scientist", "title":"The Scientist"},


    {"name":"naturalist", "title":"The Naturalist"},
    {"name":"survivalist", "title":"The Survivalist"},
    {"name":"explorer", "title":"The Explorer"},
    {"name":"discoverer", "title":"The Discoverer"},
    {"name":"astronomer", "title":"The Astronomer"},

    {"name":"dancer", "title":"The Dancer"},
    {"name":"athlete", "title":"The Athlete"},
    {"name":"bodybuilder", "title":"The Bodybuilder"},
    {"name":"luminary", "title":"The Luminary"},


    {"name":"chef", "title":"The Chef"},
    {"name":"blacksmith", "title":"The Blacksmith"},
    {"name":"maker", "title":"The Maker"},

    {"name":"dj", "title":"The DJ"},
    {"name":"musician", "title":"The Musician"},
    {"name":"composer", "title":"The Composer"},
    {"name":"poet", "title":"The Poet"},

    {"name":"sculptor", "title":"The Sculptor"},
    {"name":"photographer", "title":"The Photographer"},

    {"name":"artist", "title":"The Artist"},
    {"name":"designer", "title":"The Designer"},
    {"name":"graffitist", "title":"The Graffitist"},


    {"name":"hacker", "title":"The Hacker"},
    {"name":"wizard", "title":"The Wizard"},
    {"name":"guru", "title":"The Guru"},
    {"name":"programmer", "title":"The Programmer"},
    {"name":"web-developer", "title":"The Web Developer"},

    {"name":"highschooler", "title":"The Highschooler"},

    {"name":"principal", "title":"The Principal"},
    {"name":"teacher", "title":"The Teacher"},
    {"name":"student", "title":"The Student"},

    {"name":"genius", "title":"The Genius"},

    {"name":"courageous", "title":"The Courageous"},

    {"name":"visionary", "title":"The Visionary"},
    {"name":"founder", "title":"The Founder"}



  ]

}
